vertvideo/__init__.py
vertvideo/__main__.py
vertvideo/version.py
vertvideo-1.0.1.dist-info/LICENCE
vertvideo-1.0.1.dist-info/METADATA
vertvideo-1.0.1.dist-info/WHEEL
vertvideo-1.0.1.dist-info/entry_points.txt
vertvideo-1.0.1.dist-info/top_level.txt
vertvideo-1.0.1.dist-info/RECORD
